simplejustwatchapi/__init__.py
simplejustwatchapi/justwatch.py
simplejustwatchapi/main.py
simplejustwatchapi/query.py
simple_justwatch_python_api-0.16.dist-info/LICENSE
simple_justwatch_python_api-0.16.dist-info/METADATA
simple_justwatch_python_api-0.16.dist-info/WHEEL
simple_justwatch_python_api-0.16.dist-info/top_level.txt
simple_justwatch_python_api-0.16.dist-info/RECORD
