Metadata-Version: 2.1
Name: simple-justwatch-python-api
Version: 0.16
Summary: A simple JustWatch Python API
Author-email: Electronic Mango <78230210+Electronic-Mango@users.noreply.github.com>
License: GNU GENERAL PUBLIC LICENSE
Project-URL: Homepage, https://github.com/Electronic-Mango/simple-justwatch-python-api
Project-URL: Documentation, https://electronic-mango.github.io/simple-justwatch-python-api
Project-URL: Repository, https://github.com/Electronic-Mango/simple-justwatch-python-api
Keywords: justwatch,api,graphql
Classifier: Development Status :: 3 - Alpha
Classifier: Intended Audience :: Developers
Classifier: Topic :: Software Development :: Build Tools
Classifier: License :: OSI Approved :: GNU General Public License v3 (GPLv3)
Classifier: Programming Language :: Python :: 3
Classifier: Programming Language :: Python :: 3.11
Requires-Python: >=3.11
License-File: LICENSE
Requires-Dist: httpx
